{
  "_source": [
      "charity_number",
      "website",
      "facebook",
      "twitter",
      "linkedin",
      "instagram",
      "title",
      "image_url",
      "rendered.goodhq_heart_rating",
      "rendered.goodhq_hearts",
  ],
  "query": {
    "ids": {
      "type": "goodhq-organisation",
      "values": [
        {{{stringify (default @root.data.primaryResponse.hits.hits.[0]._source.goodhq-xid-1 "")}}},
        {{{stringify (default @root.data.primaryResponse.hits.hits.[0]._source.goodhq-xid-2 "")}}},
        {{{stringify (default @root.data.primaryResponse.hits.hits.[0]._source.goodhq-xid-3 "")}}},
      ]
    }
  }
}